README.md
setup.py
django_raise.egg-info/PKG-INFO
django_raise.egg-info/SOURCES.txt
django_raise.egg-info/dependency_links.txt
django_raise.egg-info/top_level.txt
raiseapp/__init__.py
raiseapp/admin.py
raiseapp/apps.py
raiseapp/forms.py
raiseapp/models.py
raiseapp/tests.py
raiseapp/urls.py
raiseapp/views.py
raiseapp/migrations/0001_initial.py
raiseapp/migrations/0002_reward_timeframe.py
raiseapp/migrations/0003_auto_20180128_1754.py
raiseapp/migrations/__init__.py