Metadata-Version: 1.1
Name: django-raise
Version: 0.0.7
Summary: Raise money from pledges
Home-page: https://github.com/AvocadoCoop/django-raise
Author: Avocado Co-op
Author-email: albert@avocado.coop
License: UNKNOWN
Platform: UNKNOWN
Classifier: Development Status :: 3 - Alpha
Classifier: License :: OSI Approved :: MIT License
Classifier: Programming Language :: Python :: 3
Classifier: Programming Language :: Python :: 3.6
